aqualink/__init__.py
aqualink/connection.py
aqualink/eq.py
aqualink/exceptions.py
aqualink/player.py
aqualink/track.py
aqualink-1.0.0.dist-info/LICENSE
aqualink-1.0.0.dist-info/METADATA
aqualink-1.0.0.dist-info/WHEEL
aqualink-1.0.0.dist-info/top_level.txt
aqualink-1.0.0.dist-info/RECORD
