Metadata-Version: 2.1
Name: aqualink
Version: 1.0.0
Summary: A better Python lavalink client
Home-page: https://github.com/nanipy/aqualink
Author: Gelbpunkt & F4stZ4p
Author-email: aqualink@is-the.best
License: MIT
Platform: UNKNOWN
Classifier: Programming Language :: Python :: 3.6
Classifier: License :: OSI Approved :: MIT License
Classifier: Operating System :: OS Independent
Requires-Dist: websockets
Requires-Dist: aiohttp
Requires-Dist: ujson
